{
	"id": "927da463-9361-4153-8c2b-c0270a2d41bf",
	"name": "Solarman",
	"values": [
		{
			"key": "SolarmanEmail",
			"value": "youremail@yourdomain.com",
			"type": "default",
			"enabled": true
		},
		{
			"key": "SolarmanPasswordSHA256",
			"value": "64_byte_hex_string",
			"type": "secret",
			"enabled": true
		},
		{
			"key": "appId",
			"value": "123456789012345",
			"type": "secret",
			"enabled": true
		},
		{
			"key": "SolarmanSecret",
			"value": "32_byte_hex_string",
			"type": "secret",
			"enabled": true
		},
		{
			"key": "SolarmanBearerToken",
			"value": "",
			"type": "secret",
			"enabled": true
		},
		{
			"key": "deviceSn",
			"value": "1234567890-1",
			"type": "secret",
			"enabled": true
		},
		{
			"key": "stationId",
			"value": "1234567",
			"type": "secret",
			"enabled": true
		}
	],
	"_postman_variable_scope": "environment",
	"_postman_exported_at": "2022-09-03T21:58:20.448Z",
	"_postman_exported_using": "Postman/9.29.0"
}